Metadata-Version: 2.4
Name: fapier
Version: 0.1.5
Summary: A command-line tool to scaffold and bootstrap FastAPI projects quickly.
Author: Dahmoun Mouaine Aymen
License: MIT
Project-URL: Homepage, https://github.com/aymen-dahmoun/fapi
Project-URL: Repository, https://github.com/aymen-dahmoun/fapi
Requires-Python: >=3.10
Requires-Dist: fastapi
Requires-Dist: uvicorn[standard]
Requires-Dist: typer[all]
Requires-Dist: jinja2
Requires-Dist: sqlalchemy
Requires-Dist: passlib[bcrypt]
Requires-Dist: pydantic[email]
Requires-Dist: python-dotenv
Requires-Dist: pydantic-settings
